odoo/addons/account_analytic_parent/README.rst
odoo/addons/account_analytic_parent/__init__.py
odoo/addons/account_analytic_parent/__manifest__.py
odoo/addons/account_analytic_parent/hooks.py
odoo/addons/account_analytic_parent/data/analytic_account_demo.xml
odoo/addons/account_analytic_parent/i18n/account_analytic_parent.pot
odoo/addons/account_analytic_parent/i18n/ca.po
odoo/addons/account_analytic_parent/i18n/cs_CZ.po
odoo/addons/account_analytic_parent/i18n/de.po
odoo/addons/account_analytic_parent/i18n/el_GR.po
odoo/addons/account_analytic_parent/i18n/es.po
odoo/addons/account_analytic_parent/i18n/es_EC.po
odoo/addons/account_analytic_parent/i18n/es_MX.po
odoo/addons/account_analytic_parent/i18n/fi.po
odoo/addons/account_analytic_parent/i18n/fr.po
odoo/addons/account_analytic_parent/i18n/gl.po
odoo/addons/account_analytic_parent/i18n/gl_ES.po
odoo/addons/account_analytic_parent/i18n/gu_IN.po
odoo/addons/account_analytic_parent/i18n/hi_IN.po
odoo/addons/account_analytic_parent/i18n/hr.po
odoo/addons/account_analytic_parent/i18n/hr_HR.po
odoo/addons/account_analytic_parent/i18n/it.po
odoo/addons/account_analytic_parent/i18n/nl.po
odoo/addons/account_analytic_parent/i18n/nl_NL.po
odoo/addons/account_analytic_parent/i18n/pt.po
odoo/addons/account_analytic_parent/i18n/pt_BR.po
odoo/addons/account_analytic_parent/i18n/ru.po
odoo/addons/account_analytic_parent/i18n/sk_SK.po
odoo/addons/account_analytic_parent/i18n/sl.po
odoo/addons/account_analytic_parent/i18n/zh_CN.po
odoo/addons/account_analytic_parent/models/__init__.py
odoo/addons/account_analytic_parent/models/account_analytic_account.py
odoo/addons/account_analytic_parent/readme/CONTRIBUTORS.rst
odoo/addons/account_analytic_parent/readme/DESCRIPTION.rst
odoo/addons/account_analytic_parent/readme/USAGE.rst
odoo/addons/account_analytic_parent/static/description/icon.png
odoo/addons/account_analytic_parent/static/description/index.html
odoo/addons/account_analytic_parent/tests/__init__.py
odoo12_addon_account_analytic_parent-12.0.2.3.1.dist-info/METADATA
odoo12_addon_account_analytic_parent-12.0.2.3.1.dist-info/WHEEL
odoo12_addon_account_analytic_parent-12.0.2.3.1.dist-info/top_level.txt
odoo12_addon_account_analytic_parent-12.0.2.3.1.dist-info/RECORD
