Metadata-Version: 2.1
Name: odoo12-addon-account-analytic-parent
Version: 12.0.2.3.1
Summary: This module reintroduces the hierarchy to the analytic accounts.
Home-page: https://www.github.com/OCA/account-analytic.git
Author: Matmoz d.o.o., Luxim d.o.o., Deneroteam, Eficent, Tecnativa, Brainbean Apps, Odoo Community Association (OCA)
Author-email: support@odoo-community.org
License: AGPL-3
Platform: UNKNOWN
Classifier: Programming Language :: Python
Classifier: Framework :: Odoo
Classifier: License :: OSI Approved :: GNU Affero General Public License v3
Requires-Python: >=3.5
Requires-Dist: odoo (<12.1dev,>=12.0a)
